ob_tuner/__init__.py
ob_tuner/app.py
ob_tuner/functions/__init__.py
ob_tuner/functions/button_logic.py
ob_tuner/functions/client_functions.py
ob_tuner/landing_page.py
ob_tuner/main_page.py
ob_tuner/resources/avatars/ai-32px.png
ob_tuner/resources/avatars/emotional-intelligence.png
ob_tuner/resources/avatars/human-32px.png
ob_tuner/resources/avatars/human-dalle3.webp
ob_tuner/resources/avatars/icons8-ai-64.png
ob_tuner/resources/avatars/icons8-human-64.png
ob_tuner/resources/favicon/android-chrome-192x192.png
ob_tuner/resources/favicon/android-chrome-512x512.png
ob_tuner/resources/favicon/apple-touch-icon.png
ob_tuner/resources/favicon/favicon-16x16.png
ob_tuner/resources/favicon/favicon-32x32.png
ob_tuner/resources/favicon/favicon.ico
ob_tuner/resources/favicon/favicon.png
ob_tuner/resources/favicon/site.webmanifest
ob_tuner/resources/help_text.md
ob_tuner/util.py
ob_tuner-5.1.0.dist-info/METADATA
ob_tuner-5.1.0.dist-info/WHEEL
ob_tuner-5.1.0.dist-info/entry_points.txt
ob_tuner-5.1.0.dist-info/RECORD
