Metadata-Version: 2.3
Name: ob-tuner
Version: 5.1.0
Summary: OpenBra.in agent creation and tuning Gradio deployment.
Author: Samuel Vange
Author-email: 7166607+svange@users.noreply.github.com
Requires-Python: >=3.10,<4.0
Classifier: Programming Language :: Python :: 3
Classifier: Programming Language :: Python :: 3.10
Classifier: Programming Language :: Python :: 3.11
Classifier: Programming Language :: Python :: 3.12
Classifier: Programming Language :: Python :: 3.13
Requires-Dist: augint-leadmo (>=1.0.0,<2.0.0)
Requires-Dist: authlib (>=1.3.1,<2.0.0)
Requires-Dist: boto3 (>=1.34.140,<2.0.0)
Requires-Dist: faker (>=19.6.1,<20.0.0)
Requires-Dist: fastapi (>=0.111.0,<0.112.0)
Requires-Dist: gradio (>=4.37.2,<5.0.0)
Requires-Dist: gtts (>=2.5.2,<3.0.0)
Requires-Dist: itsdangerous (>=2.2.0,<3.0.0)
Requires-Dist: openbrain (>=5.0.0,<6.0.0)
Requires-Dist: playwright (>=1.45.0,<2.0.0)
Requires-Dist: pycryptodome (>=3.20.0,<4.0.0)
Requires-Dist: pyjwt (>=2.8.0,<3.0.0)
Requires-Dist: requests (>=2.32.3,<3.0.0)
Requires-Dist: starlette (>=0.37.2,<0.38.0)
Requires-Dist: uvicorn (>=0.30.1,<0.31.0)
Project-URL: Homepage, https://github.com/svange/openbrain
